{"eRI_UNUSED31":31,"eRI_UNUSED30":30,"eRI_UNUSED27":27,"eRI_SAFE":8,"eRI_GARDEN_PLANE":17,"eRI_UNUSED29":29,"eRI_PLAY3":25,"eRI_UNUSED26":26,"eRI_PK":10,"eRI_UNUSED7":7,"eRI_NO_RIDING":16,"eRI_UNUSED28":28,"eRI_GARDEN_BAY":18,"eRI_GRASS":11,"eRI_YABIAOREGION":22,"eRI_GUILD_DESIGN":23,"eRI_VEND2":21,"eRI_GUILD_SAFE":14,"eRI_GARDEN_EXTEND":20,"eRI_PLAY2":13,"eRI_GARDEN_WATER":19,"eRI_UNUSED6":6,"eRI_PLAY1":12,"eRI_VEND":9,"eRI_UNUSED5":5,"eRI_ANTI_ROAD":3,"eRI_UNUSED4":4,"eRI_CLIFF":2,"eRI_DIG":24,"eRI_NO_MONSTER":15,"eRI_SKILL":1,"eRI_ROAD":0}